influxbc/__init__.py
influxbc/_base.py
influxbc/client_v1.py
influxbc/client_v2.py
influxbc/const.py
influxbc/errors.py
influxbc/logging.py
influxbc/typing.py
influxbc-0.1.3.dist-info/LICENSE
influxbc-0.1.3.dist-info/METADATA
influxbc-0.1.3.dist-info/WHEEL
influxbc-0.1.3.dist-info/RECORD
