Metadata-Version: 2.1
Name: influxbc
Version: 0.1.3
Summary: A universal Python client for InfluxDB
Home-page: https://gitlab.com/waermewerk/influxbc
License: MIT
Author: Paul Kernstock
Author-email: paul.kernstock@posteo.de
Maintainer: Paul Kernstock
Maintainer-email: paul.kernstock@posteo.de
Requires-Python: >=3.8,<3.13
Classifier: License :: OSI Approved :: MIT License
Classifier: Programming Language :: Python :: 3
Classifier: Programming Language :: Python :: 3.8
Classifier: Programming Language :: Python :: 3.9
Classifier: Programming Language :: Python :: 3.10
Classifier: Programming Language :: Python :: 3.11
Classifier: Programming Language :: Python :: 3.12
Requires-Dist: influxdb (>=5,<6)
Requires-Dist: influxdb-client[extra] (>=1,<2)
Requires-Dist: pandas (>=2,<3)
Project-URL: Changelog, https://gitlab.com/waermewerk/influxbc/blob/main/CHANGELOG.md
Project-URL: Issues, https://gitlab.com/waermewerk/influxbc/issues
Project-URL: Repository, https://gitlab.com/waermewerk/influxbc
